grafana_import/__init__.py
grafana_import/cli.py
grafana_import/constants.py
grafana_import/grafana.py
grafana_import/service.py
grafana_import/util.py
grafana_import/conf/grafana-import.yml
tests/__init__.py
tests/conftest.py
tests/test_cli.py
tests/test_core.py
tests/test_util.py
tests/util.py
grafana_import-0.5.0.dist-info/AUTHORS.md
grafana_import-0.5.0.dist-info/LICENSE
grafana_import-0.5.0.dist-info/METADATA
grafana_import-0.5.0.dist-info/WHEEL
grafana_import-0.5.0.dist-info/entry_points.txt
grafana_import-0.5.0.dist-info/top_level.txt
grafana_import-0.5.0.dist-info/RECORD
