Metadata-Version: 2.2
Name: grafana-import
Version: 0.5.0
Summary: Export and import Grafana dashboards using the Grafana HTTP API.
Home-page: https://github.com/grafana-toolbox/grafana-import
Author: Jean-Francois Pik
Author-email: jfpik78@gmail.com
License: Apache 2.0
Keywords: grafana http api grafana-client grafana-api http-client grafana-utils grafana-automation grafana-toolbox dashboard grafana-dashboard grafanalib grafonnet
Classifier: Programming Language :: Python
Classifier: License :: OSI Approved :: Apache Software License
Classifier: Development Status :: 4 - Beta
Classifier: Environment :: Console
Classifier: Intended Audience :: Developers
Classifier: Intended Audience :: Education
Classifier: Intended Audience :: Information Technology
Classifier: Intended Audience :: Manufacturing
Classifier: Intended Audience :: Science/Research
Classifier: Intended Audience :: System Administrators
Classifier: Intended Audience :: Telecommunications Industry
Classifier: Operating System :: POSIX
Classifier: Operating System :: Unix
Classifier: Operating System :: MacOS
Classifier: Programming Language :: Python
Classifier: Programming Language :: Python :: 3.6
Classifier: Programming Language :: Python :: 3.7
Classifier: Programming Language :: Python :: 3.8
Classifier: Programming Language :: Python :: 3.9
Classifier: Programming Language :: Python :: 3.10
Classifier: Programming Language :: Python :: 3.11
Classifier: Programming Language :: Python :: 3.12
Classifier: Programming Language :: Python :: 3.13
Classifier: Topic :: Communications
Classifier: Topic :: Database
Classifier: Topic :: Internet
Classifier: Topic :: Scientific/Engineering :: Human Machine Interfaces
Classifier: Topic :: Scientific/Engineering :: Information Analysis
Classifier: Topic :: Scientific/Engineering :: Interface Engine/Protocol Translator
Classifier: Topic :: Scientific/Engineering :: Visualization
Classifier: Topic :: Software Development :: Embedded Systems
Classifier: Topic :: Software Development :: Libraries
Classifier: Topic :: System :: Archiving
Classifier: Topic :: System :: Networking :: Monitoring
License-File: LICENSE
License-File: AUTHORS.md
Requires-Dist: grafana-client<5
Requires-Dist: jinja2<4
Requires-Dist: pyyaml<7
Requires-Dist: watchdog<5
Provides-Extra: builder
Requires-Dist: grafana-dashboard==0.1.1; extra == "builder"
Requires-Dist: grafanalib==0.7.1; extra == "builder"
Provides-Extra: develop
Requires-Dist: black<25; extra == "develop"
Requires-Dist: mypy<1.10; extra == "develop"
Requires-Dist: poethepoet<0.26; extra == "develop"
Requires-Dist: pyproject-fmt<1.8; python_version >= "3.7" and extra == "develop"
Requires-Dist: ruff<0.5; python_version >= "3.7" and extra == "develop"
Requires-Dist: validate-pyproject<0.17; extra == "develop"
Provides-Extra: release
Requires-Dist: build; extra == "release"
Requires-Dist: twine; extra == "release"
Provides-Extra: test
Requires-Dist: grafana-dashboard<0.2; python_version >= "3.7" and extra == "test"
Requires-Dist: importlib-resources<7; python_version < "3.9" and extra == "test"
Requires-Dist: pydantic<2; extra == "test"
Requires-Dist: pytest<9; extra == "test"
Requires-Dist: pytest-cov<6; extra == "test"
Requires-Dist: responses<0.26; extra == "test"
Dynamic: author
Dynamic: author-email
Dynamic: classifier
Dynamic: description
Dynamic: description-content-type
Dynamic: home-page
Dynamic: keywords
Dynamic: license
Dynamic: provides-extra
Dynamic: requires-dist
Dynamic: summary
